spider/Annealing.py
spider/MainWidget.py
spider/PaintBoard.py
spider/__init__.py
spider/data_op.py
spider/enhance.py
spider/joint_simulator.py
spider/main.py
spider/opt.py
spider/random_based_utils.py
spider/random_generator.py
spider/run_scsim.py
spider/scsim.py
spider/sim_expr.py
spider/sim_naive.py
spider/simulate_10X.py
spider/utils.py
st_spider-1.1.0.dist-info/LICENSE.txt
st_spider-1.1.0.dist-info/METADATA
st_spider-1.1.0.dist-info/WHEEL
st_spider-1.1.0.dist-info/top_level.txt
st_spider-1.1.0.dist-info/RECORD
