Metadata-Version: 2.1
Name: st-spider
Version: 1.1.0
Summary: A tools to simulate spatial transcriptomics data.
Home-page: https://github.com/YANG-ERA/Spider/tree/main
Author: Jiyuan Yang
Author-email: 599568651@qq.com
License: MIT
License-File: LICENSE.txt
Requires-Dist: anndata
Requires-Dist: matplotlib
Requires-Dist: numba
Requires-Dist: numpy
Requires-Dist: pandas
Requires-Dist: scanpy
Requires-Dist: scikit-learn
Requires-Dist: scipy
Requires-Dist: seaborn
Requires-Dist: squidpy
Requires-Dist: joblib
Requires-Dist: plotly
